<PAMDataset>
  <Metadata>
    <MDI key="DataType">Generic</MDI>
  </Metadata>
  <PAMRasterBand band="1">
    <Description>Band_1</Description>
    <Histograms>
      <HistItem>
        <HistMin>6309.57666015625</HistMin>
        <HistMax>3435581.5</HistMax>
        <BucketCount>256</BucketCount>
        <IncludeOutOfRange>1</IncludeOutOfRange>
        <Approximate>0</Approximate>
        <HistCounts>39898|198|415|0|150|252|0|81|66|104|45|134|0|59|35|29|44|36|44|40|92|0|18|52|0|17|34|26|35|51|19|16|18|23|10|18|16|19|10|14|10|11|0|20|11|20|22|13|0|23|19|0|13|12|0|17|5|0|24|0|36|0|0|16|0|22|0|12|0|14|0|7|0|11|0|13|0|14|0|9|0|11|0|14|0|0|14|0|5|0|0|12|0|0|14|10|0|0|0|6|0|0|9|0|0|8|0|0|8|0|0|5|0|0|10|0|0|3|0|0|3|0|0|0|14|0|0|6|0|0|0|12|0|0|10|0|0|0|8|0|0|0|11|0|0|0|9|0|0|0|6|0|0|0|4|0|0|0|0|11|0|0|0|6|0|0|0|6|0|0|0|0|10|0|0|0|0|2|0|0|0|0|9|0|0|0|0|0|14|0|0|0|0|3|0|0|0|0|3|0|0|0|0|0|2|0|0|0|0|0|3|0|0|0|0|2|0|0|0|0|0|0|2|0|0|0|0|0|4|0|0|0|0|0|2|0|0|0|0|0|0|3|0|0|0|0|0|0|2|0|0|0|0|0|0|1</HistCounts>
      </HistItem>
    </Histograms>
    <Metadata>
      <MDI key="BandName">Band_1</MDI>
      <MDI key="RepresentationType">ATHEMATIC</MDI>
    </Metadata>
  </PAMRasterBand>
</PAMDataset>
