<PAMDataset>
  <Metadata>
    <MDI key="DataType">Generic</MDI>
  </Metadata>
  <PAMRasterBand band="1">
    <Histograms>
      <HistItem>
        <HistMin>6309.57666015625</HistMin>
        <HistMax>1018591.6875</HistMax>
        <BucketCount>256</BucketCount>
        <IncludeOutOfRange>1</IncludeOutOfRange>
        <Approximate>0</Approximate>
        <HistCounts>73804|492|389|297|262|259|234|182|137|154|121|122|142|102|55|59|86|29|50|50|57|30|65|28|16|49|46|15|50|28|11|21|43|34|19|23|23|29|14|17|28|0|30|23|27|11|0|13|5|0|18|41|0|7|20|0|14|5|0|14|0|15|2|0|9|0|9|0|11|0|8|0|9|0|10|0|5|0|6|0|0|2|0|5|0|10|0|0|10|0|0|0|0|5|0|4|0|0|7|0|0|3|0|0|4|0|0|0|0|0|6|0|0|6|0|0|2|0|0|0|9|0|0|0|0|0|0|0|0|0|5|0|0|0|0|0|0|0|4|0|0|0|2|0|0|0|4|0|0|0|0|0|0|0|6|0|0|0|0|0|0|0|0|0|0|0|0|3|0|0|0|0|0|0|0|0|0|0|0|0|0|0|0|0|0|0|0|0|0|0|0|0|0|0|0|0|0|0|3|0|0|0|0|0|0|0|0|0|0|0|0|0|0|0|0|0|0|0|0|0|0|0|0|0|0|0|0|0|0|0|0|0|0|0|0|0|0|0|0|0|0|0|0|0|0|0|0|0|0|0|0|0|0|0|0|3</HistCounts>
      </HistItem>
    </Histograms>
    <Metadata>
      <MDI key="RepresentationType">ATHEMATIC</MDI>
      <MDI key="STATISTICS_COVARIANCES">656680124.1451234</MDI>
      <MDI key="STATISTICS_EXCLUDEDVALUES"></MDI>
      <MDI key="STATISTICS_MAXIMUM">1018591.6875</MDI>
      <MDI key="STATISTICS_MEAN">9887.8729980074</MDI>
      <MDI key="STATISTICS_MEDIAN">6309.576660</MDI>
      <MDI key="STATISTICS_MINIMUM">6309.5766601562</MDI>
      <MDI key="STATISTICS_SKIPFACTORX">1</MDI>
      <MDI key="STATISTICS_SKIPFACTORY">1</MDI>
      <MDI key="STATISTICS_STDDEV">25625.770703437</MDI>
    </Metadata>
  </PAMRasterBand>
</PAMDataset>
