<PAMDataset>
  <PAMRasterBand band="1">
    <Description>Band_1</Description>
    <Histograms>
      <HistItem>
        <HistMin>6309.57666015625</HistMin>
        <HistMax>2466040.5</HistMax>
        <BucketCount>256</BucketCount>
        <IncludeOutOfRange>1</IncludeOutOfRange>
        <Approximate>0</Approximate>
        <HistCounts>28692|25|29|15|20|10|28|18|9|7|17|13|13|17|4|31|22|19|18|12|35|36|15|53|16|51|16|10|70|0|13|15|26|18|15|23|16|16|9|14|23|6|12|0|14|8|15|0|16|15|24|0|11|23|0|17|28|27|0|0|26|16|13|0|0|6|0|5|0|2|0|8|0|12|0|7|0|16|0|8|0|22|0|0|8|0|8|0|12|0|0|4|0|5|0|0|25|0|0|12|0|0|14|0|13|0|0|24|0|0|4|0|0|0|17|0|0|27|0|0|3|0|13|0|0|0|0|6|0|0|0|2|0|0|4|0|0|0|9|0|0|0|3|0|0|0|1|0|0|0|8|0|0|0|0|0|0|0|0|0|0|0|0|0|0|0|0|0|5|0|0|0|5|0|0|0|0|5|0|0|0|0|2|0|0|0|0|0|0|0|0|0|0|2|0|0|0|0|0|0|0|0|0|0|0|0|0|0|0|0|0|0|0|0|0|0|0|0|0|0|0|0|0|0|0|0|0|0|0|0|0|0|0|0|0|0|0|0|0|0|0|0|0|0|0|0|0|0|0|0|0|0|0|0|4|0</HistCounts>
      </HistItem>
    </Histograms>
  </PAMRasterBand>
</PAMDataset>
