<PAMDataset>
  <PAMRasterBand band="1">
    <Description>Band_1</Description>
    <Histograms>
      <HistItem>
        <HistMin>6309.57666015625</HistMin>
        <HistMax>6137621.5</HistMax>
        <BucketCount>256</BucketCount>
        <IncludeOutOfRange>1</IncludeOutOfRange>
        <Approximate>0</Approximate>
        <HistCounts>27371|105|77|50|74|51|49|38|41|40|29|30|10|36|67|0|25|42|34|61|64|25|81|42|61|57|207|0|78|227|0|70|79|66|92|78|73|89|102|96|78|0|100|79|102|80|0|82|78|78|103|0|92|86|0|114|99|0|105|107|0|0|83|102|0|102|0|71|0|78|0|121|0|82|0|69|0|64|0|53|0|71|0|0|57|0|56|0|0|50|0|68|0|0|43|0|47|0|32|0|0|35|0|0|34|0|0|36|0|0|35|0|0|22|0|0|37|0|0|18|0|0|0|0|31|0|0|20|0|0|0|18|0|0|14|0|0|0|9|0|0|0|12|0|0|0|17|0|0|0|11|0|0|0|18|0|0|0|0|8|0|0|0|10|0|0|0|0|10|0|0|0|0|18|0|0|0|3|0|0|0|0|9|0|0|0|0|0|4|0|0|0|0|1|0|0|0|3|0|0|0|0|0|2|0|0|0|0|0|0|0|0|0|0|0|2|0|0|0|0|0|0|0|0|0|0|0|0|0|0|0|0|0|2|0|0|0|0|0|0|0|0|0|0|0|0|0|0|3|0|0|0|0|0|0|3</HistCounts>
      </HistItem>
    </Histograms>
  </PAMRasterBand>
</PAMDataset>
