<PAMDataset>
  <PAMRasterBand band="1">
    <Description>Band_1</Description>
    <Histograms>
      <HistItem>
        <HistMin>6309.57666015625</HistMin>
        <HistMax>6486349</HistMax>
        <BucketCount>256</BucketCount>
        <IncludeOutOfRange>1</IncludeOutOfRange>
        <Approximate>0</Approximate>
        <HistCounts>26628|873|1751|0|927|1480|0|498|566|417|482|529|0|334|352|339|437|368|359|320|313|125|211|267|0|86|157|54|72|56|45|48|29|10|20|39|22|26|23|35|36|0|24|29|17|16|0|22|0|5|0|21|10|0|8|10|0|11|12|0|16|0|25|5|0|19|0|23|0|32|0|53|0|75|0|99|0|113|0|108|0|57|0|0|20|0|11|0|4|0|0|0|0|0|0|0|0|0|0|0|0|0|0|0|0|0|0|0|0|0|0|0|0|0|0|0|0|0|0|0|0|0|0|0|0|0|0|0|0|0|0|0|0|0|0|0|0|0|0|0|0|0|0|0|0|0|0|0|0|0|0|0|0|0|0|0|0|0|0|0|0|0|0|0|0|0|0|0|4|0|0|0|0|0|0|0|0|0|0|0|0|0|0|0|0|0|0|0|4|0|0|0|3|0|0|0|0|0|0|0|0|0|0|0|0|0|0|0|0|0|0|0|0|0|0|0|1|0|0|0|0|1|0|0|0|0|0|0|2|0|0|0|0|0|0|0|0|0|0|0|0|17|0|0|0|0|0|0|23|0|0|0|0|0|0|6</HistCounts>
      </HistItem>
    </Histograms>
  </PAMRasterBand>
</PAMDataset>
