<PAMDataset>
  <PAMRasterBand band="1">
    <Description>Band_1</Description>
    <Histograms>
      <HistItem>
        <HistMin>6309.57666015625</HistMin>
        <HistMax>963829.4375</HistMax>
        <BucketCount>256</BucketCount>
        <IncludeOutOfRange>1</IncludeOutOfRange>
        <Approximate>0</Approximate>
        <HistCounts>6693|69|81|0|26|50|0|45|21|33|25|45|0|9|9|26|15|20|5|15|25|11|29|24|0|9|9|10|16|15|6|10|11|11|17|14|18|13|12|6|21|0|6|16|12|2|0|26|0|0|15|11|14|0|22|0|16|23|0|14|0|17|10|0|11|0|6|0|17|0|9|0|14|0|12|0|12|0|6|0|9|0|0|10|0|14|0|0|8|0|15|0|0|1|0|9|0|0|9|0|0|8|0|0|17|0|0|21|0|0|10|0|0|21|0|0|12|0|0|0|10|0|0|18|0|0|13|0|0|0|15|0|0|0|19|0|0|0|10|0|0|9|0|0|0|0|10|0|0|0|1|0|0|0|17|0|0|0|11|0|0|0|0|17|0|0|0|3|0|0|0|0|12|0|0|0|0|22|0|0|0|0|6|0|0|0|0|10|0|0|0|0|0|4|0|0|0|0|3|0|0|0|0|0|5|0|0|0|0|12|0|0|0|0|0|0|0|0|0|0|0|0|0|0|0|0|0|0|2|0|0|0|0|0|0|0|0|0|0|0|0|0|0|0|0|0|0|0|0|0|0|0|0|0|0|3</HistCounts>
      </HistItem>
    </Histograms>
  </PAMRasterBand>
</PAMDataset>
