<PAMDataset>
  <PAMRasterBand band="1">
    <Description>Band_1</Description>
    <Histograms>
      <HistItem>
        <HistMin>6309.57666015625</HistMin>
        <HistMax>6854886</HistMax>
        <BucketCount>256</BucketCount>
        <IncludeOutOfRange>1</IncludeOutOfRange>
        <Approximate>0</Approximate>
        <HistCounts>28869|0|542|556|586|318|378|236|206|205|210|301|162|207|131|266|249|314|313|327|330|162|341|144|322|143|438|0|163|160|175|339|184|124|201|158|181|173|178|149|92|0|108|67|89|57|0|55|67|70|0|65|38|43|54|0|0|56|62|0|30|0|47|61|0|37|0|32|0|35|0|29|0|27|0|26|0|22|0|13|0|11|0|0|16|0|15|0|0|7|0|13|0|0|3|0|12|0|0|16|0|0|12|0|0|18|0|20|0|0|0|18|0|0|14|0|0|16|0|0|8|0|0|0|0|0|0|3|0|0|0|2|0|0|4|0|0|0|1|0|0|0|0|0|0|0|0|0|0|0|0|0|0|0|0|0|0|0|0|0|0|0|0|0|0|0|0|0|0|0|0|0|1|0|0|0|0|0|0|0|0|0|0|0|0|0|0|0|2|0|0|0|0|4|0|0|0|0|0|0|0|0|0|0|0|0|0|0|0|0|0|0|0|0|0|0|0|0|0|0|0|0|0|0|0|0|0|0|4|0|0|0|0|0|4|0|0|0|0|0|0|4|0|0|0|0|0|0|2|0|0|0|0|0|0|3</HistCounts>
      </HistItem>
    </Histograms>
  </PAMRasterBand>
</PAMDataset>
