<PAMDataset>
  <PAMRasterBand band="1">
    <Description>Band_1</Description>
    <Histograms>
      <HistItem>
        <HistMin>6309.57666015625</HistMin>
        <HistMax>3837073.5</HistMax>
        <BucketCount>256</BucketCount>
        <IncludeOutOfRange>1</IncludeOutOfRange>
        <Approximate>0</Approximate>
        <HistCounts>11746|214|283|292|298|165|112|141|105|140|102|175|135|98|170|96|91|121|118|93|226|0|125|131|61|59|141|105|61|73|116|50|45|42|52|59|87|0|36|38|42|32|0|40|55|26|42|0|35|39|0|27|19|29|0|28|0|28|28|0|38|26|0|20|0|38|0|12|0|39|0|34|0|24|0|31|0|23|0|18|0|32|0|9|0|0|19|0|31|0|0|7|0|0|38|0|24|0|0|23|0|0|21|0|0|13|0|0|24|0|0|22|0|0|30|0|0|24|0|0|26|0|0|0|32|0|0|24|0|0|0|28|0|0|17|0|0|0|33|0|0|0|13|0|0|0|18|0|0|0|25|0|0|0|28|0|0|0|0|14|0|0|0|9|0|0|0|2|0|0|0|0|0|20|0|0|0|9|0|0|0|0|7|0|0|0|0|0|7|0|0|0|0|6|0|0|0|0|6|0|0|0|0|0|9|0|0|0|0|0|5|0|0|0|0|0|0|0|0|0|0|0|4|0|0|0|0|0|0|0|0|0|0|0|0|0|0|0|0|0|0|0|0|0|0|0|0|0|0|0|0|0|0|0|0|4</HistCounts>
      </HistItem>
    </Histograms>
  </PAMRasterBand>
</PAMDataset>
