<PAMDataset>
  <PAMRasterBand band="1">
    <Description>Band_1</Description>
    <Histograms>
      <HistItem>
        <HistMin>6309.57666015625</HistMin>
        <HistMax>6668069</HistMax>
        <BucketCount>256</BucketCount>
        <IncludeOutOfRange>1</IncludeOutOfRange>
        <Approximate>0</Approximate>
        <HistCounts>36081|340|499|0|250|377|0|153|169|203|162|455|0|310|313|200|139|111|130|123|166|0|104|169|0|48|136|60|63|56|73|159|48|73|47|63|49|61|56|86|64|34|0|47|144|0|0|114|0|50|0|69|50|0|70|69|0|48|85|0|48|0|61|50|0|111|0|88|0|104|0|135|0|148|0|171|0|156|0|275|0|174|0|246|0|0|217|0|0|219|0|225|0|0|171|217|0|0|0|194|0|0|174|0|0|149|0|0|209|0|0|150|0|0|190|0|0|136|0|0|131|0|0|0|141|0|0|101|0|0|0|105|0|0|106|0|0|0|85|0|0|0|96|0|0|0|96|0|0|0|95|0|0|0|75|0|0|0|0|80|0|0|0|61|0|0|0|79|0|0|0|0|0|76|0|0|0|56|0|0|0|0|58|0|0|0|0|0|28|0|0|0|0|45|0|0|0|0|38|0|0|0|0|0|33|0|0|0|0|0|24|0|0|0|0|0|39|0|0|0|0|0|16|0|0|0|0|0|5|0|0|0|0|0|8|0|0|0|0|0|0|9|0|0|0|0|0|0|8|0|0|0|0|0|0|2</HistCounts>
      </HistItem>
    </Histograms>
  </PAMRasterBand>
</PAMDataset>
