<PAMDataset>
  <PAMRasterBand band="1">
    <Description>Band_1</Description>
    <Histograms>
      <HistItem>
        <HistMin>6309.57666015625</HistMin>
        <HistMax>5058249.5</HistMax>
        <BucketCount>256</BucketCount>
        <IncludeOutOfRange>1</IncludeOutOfRange>
        <Approximate>0</Approximate>
        <HistCounts>23991|329|214|158|142|135|264|0|115|81|135|91|84|221|0|127|135|149|219|240|299|158|299|114|199|135|232|187|0|83|301|0|94|84|104|81|104|87|84|82|117|0|86|107|100|88|0|81|93|111|0|142|112|0|139|127|0|141|144|0|148|182|0|165|0|169|0|153|0|179|0|197|0|143|0|179|0|178|0|167|0|186|0|0|188|0|179|0|0|218|0|200|0|0|167|0|117|0|0|162|0|0|167|0|0|174|0|0|129|0|131|0|0|0|170|0|0|119|0|0|120|0|0|120|0|0|0|128|0|0|0|79|0|0|80|0|0|0|76|0|0|0|64|0|0|0|50|0|0|0|73|0|0|0|64|0|0|0|0|38|0|0|0|56|0|0|0|0|38|0|0|0|0|35|0|0|0|29|0|0|0|0|32|0|0|0|0|0|22|0|0|0|0|40|0|0|0|0|22|0|0|0|0|0|27|0|0|0|0|0|39|0|0|0|0|26|0|0|0|0|0|23|0|0|0|0|0|0|26|0|0|0|0|0|20|0|0|0|0|0|0|8|0|0|0|0|0|4|0|0|0|0|0|0|0|4</HistCounts>
      </HistItem>
    </Histograms>
  </PAMRasterBand>
</PAMDataset>
